notrix/__init__.py
notrix/api.py
notrix/models.py
notrix-1.3.2.dist-info/LICENSE
notrix-1.3.2.dist-info/METADATA
notrix-1.3.2.dist-info/WHEEL
notrix-1.3.2.dist-info/RECORD
