Metadata-Version: 2.1
Name: notrix
Version: 1.3.2
Summary: Notrix Official Python SDK
Home-page: https://notrix.io
License: MIT
Author: SDK team
Author-email: pythonsdk@y-faces.com
Requires-Python: >=3.7,<4.0
Classifier: License :: OSI Approved :: MIT License
Classifier: Programming Language :: Python :: 3
Classifier: Programming Language :: Python :: 3.7
Classifier: Programming Language :: Python :: 3.8
Classifier: Programming Language :: Python :: 3.9
Classifier: Programming Language :: Python :: 3.10
Classifier: Programming Language :: Python :: 3.11
Classifier: Programming Language :: Python :: 3.12
Requires-Dist: requests (>=2.31.0,<3.0.0)
Project-URL: Repository, https://github.com/NotrixPay/python-sdk
